{
  "meta": {
    "$_GET": [
      {
        "type": "text",
        "name": "organization"
      },
      {
        "type": "text",
        "name": "program"
      }
    ]
  },
  "exec": {
    "steps": {
      "name": "wishlists",
      "module": "api",
      "action": "send",
      "options": {
        "url": "{{$_ENV.PROD_API+'/'+$_GET.organization+'/'+$_GET.program+'/wishlists'}}",
        "params": {
          "isSponsored": "false",
          "wishlistType": "Individual",
          "isWishlistApproved": "true",
          "sortBy": "+recipient.household.shortId",
          "skip": "{{$_GET.skip}}",
          "take": "{{$_GET.take}}"
        },
        "schema": [
          {
            "type": "object",
            "name": "data",
            "sub": [
              {
                "type": "text",
                "name": "message"
              },
              {
                "type": "array",
                "name": "data",
                "sub": [
                  {
                    "type": "text",
                    "name": "bannerImage"
                  },
                  {
                    "type": "text",
                    "name": "circumstances"
                  },
                  {
                    "type": "text",
                    "name": "createdDatetime"
                  },
                  {
                    "type": "text",
                    "name": "donation"
                  },
                  {
                    "type": "text",
                    "name": "household"
                  },
                  {
                    "type": "number",
                    "name": "householdPosition"
                  },
                  {
                    "type": "number",
                    "name": "householdTotal"
                  },
                  {
                    "type": "text",
                    "name": "id"
                  },
                  {
                    "type": "text",
                    "name": "isPublic"
                  },
                  {
                    "type": "boolean",
                    "name": "isSponsored"
                  },
                  {
                    "type": "boolean",
                    "name": "isWishlistApproved"
                  },
                  {
                    "type": "text",
                    "name": "modifiedDatetime"
                  },
                  {
                    "type": "number",
                    "name": "numApprovedRequests"
                  },
                  {
                    "type": "number",
                    "name": "numPurchasedRequests"
                  },
                  {
                    "type": "number",
                    "name": "numTotalRequests"
                  },
                  {
                    "type": "object",
                    "name": "organization",
                    "sub": [
                      {
                        "type": "text",
                        "name": "bannerImageUrl"
                      },
                      {
                        "type": "text",
                        "name": "city"
                      },
                      {
                        "type": "text",
                        "name": "contactEmail"
                      },
                      {
                        "type": "text",
                        "name": "contactPhone"
                      },
                      {
                        "type": "text",
                        "name": "createdDatetime"
                      },
                      {
                        "type": "text",
                        "name": "description"
                      },
                      {
                        "type": "text",
                        "name": "domain"
                      },
                      {
                        "type": "text",
                        "name": "ein"
                      },
                      {
                        "type": "text",
                        "name": "email"
                      },
                      {
                        "type": "text",
                        "name": "facebook"
                      },
                      {
                        "type": "text",
                        "name": "href"
                      },
                      {
                        "type": "text",
                        "name": "id"
                      },
                      {
                        "type": "text",
                        "name": "instagram"
                      },
                      {
                        "type": "text",
                        "name": "latitude"
                      },
                      {
                        "type": "text",
                        "name": "linkedin"
                      },
                      {
                        "type": "text",
                        "name": "logoUrl"
                      },
                      {
                        "type": "text",
                        "name": "longitude"
                      },
                      {
                        "type": "text",
                        "name": "missionStatement"
                      },
                      {
                        "type": "text",
                        "name": "modifiedDatetime"
                      },
                      {
                        "type": "text",
                        "name": "name"
                      },
                      {
                        "type": "text",
                        "name": "organizationType"
                      },
                      {
                        "type": "text",
                        "name": "phone"
                      },
                      {
                        "type": "text",
                        "name": "postalCode"
                      },
                      {
                        "type": "text",
                        "name": "shortId"
                      },
                      {
                        "type": "text",
                        "name": "slug"
                      },
                      {
                        "type": "text",
                        "name": "state"
                      },
                      {
                        "type": "text",
                        "name": "streetAddress"
                      },
                      {
                        "type": "text",
                        "name": "streetAddress2"
                      },
                      {
                        "type": "object",
                        "name": "user",
                        "sub": [
                          {
                            "type": "text",
                            "name": "createdDatetime"
                          },
                          {
                            "type": "text",
                            "name": "email"
                          },
                          {
                            "type": "boolean",
                            "name": "emailSubscribed"
                          },
                          {
                            "type": "text",
                            "name": "id"
                          },
                          {
                            "type": "text",
                            "name": "modifiedDatetime"
                          },
                          {
                            "type": "text",
                            "name": "name"
                          },
                          {
                            "type": "text",
                            "name": "phone"
                          },
                          {
                            "type": "text",
                            "name": "referralSource"
                          },
                          {
                            "type": "boolean",
                            "name": "smsSubscribed"
                          },
                          {
                            "type": "text",
                            "name": "userId"
                          },
                          {
                            "type": "text",
                            "name": "userType"
                          },
                          {
                            "type": "text",
                            "name": "username"
                          }
                        ]
                      },
                      {
                        "type": "text",
                        "name": "websiteUrl"
                      }
                    ]
                  },
                  {
                    "type": "object",
                    "name": "parentWishlist",
                    "sub": [
                      {
                        "type": "text",
                        "name": "bannerImage"
                      },
                      {
                        "type": "text",
                        "name": "circumstances"
                      },
                      {
                        "type": "text",
                        "name": "createdDatetime"
                      },
                      {
                        "type": "text",
                        "name": "donation"
                      },
                      {
                        "type": "object",
                        "name": "household",
                        "sub": [
                          {
                            "type": "text",
                            "name": "city"
                          },
                          {
                            "type": "text",
                            "name": "createdDatetime"
                          },
                          {
                            "type": "text",
                            "name": "fullAddress"
                          },
                          {
                            "type": "array",
                            "name": "headsOfHousehold",
                            "sub": [
                              {
                                "type": "text",
                                "name": "age"
                              },
                              {
                                "type": "text",
                                "name": "createdDatetime"
                              },
                              {
                                "type": "text",
                                "name": "dateOfBirth"
                              },
                              {
                                "type": "text",
                                "name": "disabilityStatus"
                              },
                              {
                                "type": "text",
                                "name": "email"
                              },
                              {
                                "type": "text",
                                "name": "employmentStatus"
                              },
                              {
                                "type": "text",
                                "name": "ethnicity"
                              },
                              {
                                "type": "text",
                                "name": "firstName"
                              },
                              {
                                "type": "text",
                                "name": "fullName"
                              },
                              {
                                "type": "text",
                                "name": "gender"
                              },
                              {
                                "type": "text",
                                "name": "housingStatus"
                              },
                              {
                                "type": "text",
                                "name": "id"
                              },
                              {
                                "type": "text",
                                "name": "languagesSpoken"
                              },
                              {
                                "type": "text",
                                "name": "lastName"
                              },
                              {
                                "type": "text",
                                "name": "modifiedDatetime"
                              },
                              {
                                "type": "text",
                                "name": "personType"
                              },
                              {
                                "type": "text",
                                "name": "phone"
                              },
                              {
                                "type": "array",
                                "name": "race",
                                "sub": [
                                  {
                                    "type": "text",
                                    "name": "$value"
                                  }
                                ]
                              },
                              {
                                "type": "text",
                                "name": "shortId"
                              },
                              {
                                "type": "text",
                                "name": "suffix"
                              },
                              {
                                "type": "text",
                                "name": "transportStatus"
                              },
                              {
                                "type": "object",
                                "name": "user",
                                "sub": [
                                  {
                                    "type": "text",
                                    "name": "createdDatetime"
                                  },
                                  {
                                    "type": "text",
                                    "name": "email"
                                  },
                                  {
                                    "type": "boolean",
                                    "name": "emailSubscribed"
                                  },
                                  {
                                    "type": "text",
                                    "name": "id"
                                  },
                                  {
                                    "type": "text",
                                    "name": "modifiedDatetime"
                                  },
                                  {
                                    "type": "text",
                                    "name": "name"
                                  },
                                  {
                                    "type": "text",
                                    "name": "phone"
                                  },
                                  {
                                    "type": "text",
                                    "name": "referralSource"
                                  },
                                  {
                                    "type": "boolean",
                                    "name": "smsSubscribed"
                                  },
                                  {
                                    "type": "text",
                                    "name": "userId"
                                  },
                                  {
                                    "type": "text",
                                    "name": "userType"
                                  },
                                  {
                                    "type": "text",
                                    "name": "username"
                                  }
                                ]
                              },
                              {
                                "type": "text",
                                "name": "username"
                              }
                            ]
                          },
                          {
                            "type": "text",
                            "name": "householdIncome"
                          },
                          {
                            "type": "array",
                            "name": "householdMembers",
                            "sub": [
                              {
                                "type": "text",
                                "name": "age"
                              },
                              {
                                "type": "text",
                                "name": "createdDatetime"
                              },
                              {
                                "type": "text",
                                "name": "dateOfBirth"
                              },
                              {
                                "type": "text",
                                "name": "disabilityStatus"
                              },
                              {
                                "type": "text",
                                "name": "employmentStatus"
                              },
                              {
                                "type": "text",
                                "name": "ethnicity"
                              },
                              {
                                "type": "text",
                                "name": "firstName"
                              },
                              {
                                "type": "text",
                                "name": "fullName"
                              },
                              {
                                "type": "text",
                                "name": "gender"
                              },
                              {
                                "type": "text",
                                "name": "housingStatus"
                              },
                              {
                                "type": "text",
                                "name": "id"
                              },
                              {
                                "type": "text",
                                "name": "languagesSpoken"
                              },
                              {
                                "type": "text",
                                "name": "lastName"
                              },
                              {
                                "type": "text",
                                "name": "modifiedDatetime"
                              },
                              {
                                "type": "text",
                                "name": "personType"
                              },
                              {
                                "type": "array",
                                "name": "race",
                                "sub": [
                                  {
                                    "type": "text",
                                    "name": "$value"
                                  }
                                ]
                              },
                              {
                                "type": "text",
                                "name": "shortId"
                              },
                              {
                                "type": "text",
                                "name": "suffix"
                              },
                              {
                                "type": "text",
                                "name": "transportStatus"
                              },
                              {
                                "type": "text",
                                "name": "user"
                              }
                            ]
                          },
                          {
                            "type": "text",
                            "name": "id"
                          },
                          {
                            "type": "number",
                            "name": "latitude"
                          },
                          {
                            "type": "number",
                            "name": "longitude"
                          },
                          {
                            "type": "text",
                            "name": "modifiedDatetime"
                          },
                          {
                            "type": "text",
                            "name": "name"
                          },
                          {
                            "type": "text",
                            "name": "postalCode"
                          },
                          {
                            "type": "text",
                            "name": "shortId"
                          },
                          {
                            "type": "text",
                            "name": "state"
                          },
                          {
                            "type": "text",
                            "name": "streetAddress"
                          },
                          {
                            "type": "text",
                            "name": "streetAddress2"
                          }
                        ]
                      },
                      {
                        "type": "text",
                        "name": "householdPosition"
                      },
                      {
                        "type": "number",
                        "name": "householdTotal"
                      },
                      {
                        "type": "text",
                        "name": "id"
                      },
                      {
                        "type": "text",
                        "name": "isPublic"
                      },
                      {
                        "type": "boolean",
                        "name": "isSponsored"
                      },
                      {
                        "type": "boolean",
                        "name": "isWishlistApproved"
                      },
                      {
                        "type": "text",
                        "name": "modifiedDatetime"
                      },
                      {
                        "type": "number",
                        "name": "numApprovedRequests"
                      },
                      {
                        "type": "number",
                        "name": "numPurchasedRequests"
                      },
                      {
                        "type": "number",
                        "name": "numTotalRequests"
                      },
                      {
                        "type": "object",
                        "name": "organization",
                        "sub": [
                          {
                            "type": "text",
                            "name": "bannerImageUrl"
                          },
                          {
                            "type": "text",
                            "name": "city"
                          },
                          {
                            "type": "text",
                            "name": "contactEmail"
                          },
                          {
                            "type": "text",
                            "name": "contactPhone"
                          },
                          {
                            "type": "text",
                            "name": "createdDatetime"
                          },
                          {
                            "type": "text",
                            "name": "description"
                          },
                          {
                            "type": "text",
                            "name": "domain"
                          },
                          {
                            "type": "text",
                            "name": "ein"
                          },
                          {
                            "type": "text",
                            "name": "email"
                          },
                          {
                            "type": "text",
                            "name": "facebook"
                          },
                          {
                            "type": "text",
                            "name": "href"
                          },
                          {
                            "type": "text",
                            "name": "id"
                          },
                          {
                            "type": "text",
                            "name": "instagram"
                          },
                          {
                            "type": "text",
                            "name": "latitude"
                          },
                          {
                            "type": "text",
                            "name": "linkedin"
                          },
                          {
                            "type": "text",
                            "name": "logoUrl"
                          },
                          {
                            "type": "text",
                            "name": "longitude"
                          },
                          {
                            "type": "text",
                            "name": "missionStatement"
                          },
                          {
                            "type": "text",
                            "name": "modifiedDatetime"
                          },
                          {
                            "type": "text",
                            "name": "name"
                          },
                          {
                            "type": "text",
                            "name": "organizationType"
                          },
                          {
                            "type": "text",
                            "name": "phone"
                          },
                          {
                            "type": "text",
                            "name": "postalCode"
                          },
                          {
                            "type": "text",
                            "name": "shortId"
                          },
                          {
                            "type": "text",
                            "name": "slug"
                          },
                          {
                            "type": "text",
                            "name": "state"
                          },
                          {
                            "type": "text",
                            "name": "streetAddress"
                          },
                          {
                            "type": "text",
                            "name": "streetAddress2"
                          },
                          {
                            "type": "object",
                            "name": "user",
                            "sub": [
                              {
                                "type": "text",
                                "name": "createdDatetime"
                              },
                              {
                                "type": "text",
                                "name": "email"
                              },
                              {
                                "type": "boolean",
                                "name": "emailSubscribed"
                              },
                              {
                                "type": "text",
                                "name": "id"
                              },
                              {
                                "type": "text",
                                "name": "modifiedDatetime"
                              },
                              {
                                "type": "text",
                                "name": "name"
                              },
                              {
                                "type": "text",
                                "name": "phone"
                              },
                              {
                                "type": "text",
                                "name": "referralSource"
                              },
                              {
                                "type": "boolean",
                                "name": "smsSubscribed"
                              },
                              {
                                "type": "text",
                                "name": "userId"
                              },
                              {
                                "type": "text",
                                "name": "userType"
                              },
                              {
                                "type": "text",
                                "name": "username"
                              }
                            ]
                          },
                          {
                            "type": "text",
                            "name": "websiteUrl"
                          }
                        ]
                      },
                      {
                        "type": "text",
                        "name": "parentWishlist"
                      },
                      {
                        "type": "text",
                        "name": "pickupTimeslot"
                      },
                      {
                        "type": "object",
                        "name": "program",
                        "sub": [
                          {
                            "type": "boolean",
                            "name": "allowInKindDonations"
                          },
                          {
                            "type": "boolean",
                            "name": "allowMonetaryDonations"
                          },
                          {
                            "type": "text",
                            "name": "applicationReasonText"
                          },
                          {
                            "type": "text",
                            "name": "id"
                          },
                          {
                            "type": "text",
                            "name": "maximumDateOfBirth"
                          },
                          {
                            "type": "number",
                            "name": "maximumWishlistLength"
                          },
                          {
                            "type": "text",
                            "name": "minimumDateOfBirth"
                          },
                          {
                            "type": "number",
                            "name": "minimumWishlistLength"
                          },
                          {
                            "type": "text",
                            "name": "name"
                          },
                          {
                            "type": "object",
                            "name": "owner",
                            "sub": [
                              {
                                "type": "text",
                                "name": "domain"
                              },
                              {
                                "type": "text",
                                "name": "id"
                              },
                              {
                                "type": "text",
                                "name": "name"
                              },
                              {
                                "type": "text",
                                "name": "slug"
                              }
                            ]
                          },
                          {
                            "type": "text",
                            "name": "slug"
                          },
                          {
                            "type": "text",
                            "name": "sponsorshipType"
                          },
                          {
                            "type": "array",
                            "name": "wishlistQuestions",
                            "sub": [
                              {
                                "type": "text",
                                "name": "type"
                              },
                              {
                                "type": "text",
                                "name": "label"
                              },
                              {
                                "type": "boolean",
                                "name": "required"
                              }
                            ]
                          }
                        ]
                      },
                      {
                        "type": "text",
                        "name": "recipient"
                      },
                      {
                        "type": "array",
                        "name": "requests"
                      },
                      {
                        "type": "text",
                        "name": "shortId"
                      },
                      {
                        "type": "text",
                        "name": "tagIdentifier"
                      },
                      {
                        "type": "number",
                        "name": "totalValueInUsd"
                      },
                      {
                        "type": "text",
                        "name": "wishlistQuestionResponses"
                      },
                      {
                        "type": "text",
                        "name": "wishlistType"
                      }
                    ]
                  },
                  {
                    "type": "text",
                    "name": "pickupTimeslot"
                  },
                  {
                    "type": "object",
                    "name": "program",
                    "sub": [
                      {
                        "type": "boolean",
                        "name": "allowInKindDonations"
                      },
                      {
                        "type": "boolean",
                        "name": "allowMonetaryDonations"
                      },
                      {
                        "type": "text",
                        "name": "applicationReasonText"
                      },
                      {
                        "type": "text",
                        "name": "id"
                      },
                      {
                        "type": "text",
                        "name": "maximumDateOfBirth"
                      },
                      {
                        "type": "number",
                        "name": "maximumWishlistLength"
                      },
                      {
                        "type": "text",
                        "name": "minimumDateOfBirth"
                      },
                      {
                        "type": "number",
                        "name": "minimumWishlistLength"
                      },
                      {
                        "type": "text",
                        "name": "name"
                      },
                      {
                        "type": "object",
                        "name": "owner",
                        "sub": [
                          {
                            "type": "text",
                            "name": "domain"
                          },
                          {
                            "type": "text",
                            "name": "id"
                          },
                          {
                            "type": "text",
                            "name": "name"
                          },
                          {
                            "type": "text",
                            "name": "slug"
                          }
                        ]
                      },
                      {
                        "type": "text",
                        "name": "slug"
                      },
                      {
                        "type": "text",
                        "name": "sponsorshipType"
                      },
                      {
                        "type": "array",
                        "name": "wishlistQuestions",
                        "sub": [
                          {
                            "type": "text",
                            "name": "type"
                          },
                          {
                            "type": "text",
                            "name": "label"
                          },
                          {
                            "type": "boolean",
                            "name": "required"
                          }
                        ]
                      }
                    ]
                  },
                  {
                    "type": "object",
                    "name": "recipient",
                    "sub": [
                      {
                        "type": "text",
                        "name": "age"
                      },
                      {
                        "type": "text",
                        "name": "createdDatetime"
                      },
                      {
                        "type": "text",
                        "name": "dateOfBirth"
                      },
                      {
                        "type": "text",
                        "name": "disabilityStatus"
                      },
                      {
                        "type": "text",
                        "name": "employmentStatus"
                      },
                      {
                        "type": "text",
                        "name": "ethnicity"
                      },
                      {
                        "type": "text",
                        "name": "firstName"
                      },
                      {
                        "type": "text",
                        "name": "fullName"
                      },
                      {
                        "type": "text",
                        "name": "gender"
                      },
                      {
                        "type": "object",
                        "name": "household",
                        "sub": [
                          {
                            "type": "text",
                            "name": "city"
                          },
                          {
                            "type": "text",
                            "name": "createdDatetime"
                          },
                          {
                            "type": "text",
                            "name": "fullAddress"
                          },
                          {
                            "type": "text",
                            "name": "householdIncome"
                          },
                          {
                            "type": "text",
                            "name": "id"
                          },
                          {
                            "type": "number",
                            "name": "latitude"
                          },
                          {
                            "type": "number",
                            "name": "longitude"
                          },
                          {
                            "type": "text",
                            "name": "modifiedDatetime"
                          },
                          {
                            "type": "text",
                            "name": "name"
                          },
                          {
                            "type": "text",
                            "name": "postalCode"
                          },
                          {
                            "type": "text",
                            "name": "shortId"
                          },
                          {
                            "type": "text",
                            "name": "state"
                          },
                          {
                            "type": "text",
                            "name": "streetAddress"
                          },
                          {
                            "type": "text",
                            "name": "streetAddress2"
                          }
                        ]
                      },
                      {
                        "type": "text",
                        "name": "housingStatus"
                      },
                      {
                        "type": "text",
                        "name": "id"
                      },
                      {
                        "type": "text",
                        "name": "languagesSpoken"
                      },
                      {
                        "type": "text",
                        "name": "lastName"
                      },
                      {
                        "type": "text",
                        "name": "modifiedDatetime"
                      },
                      {
                        "type": "text",
                        "name": "personType"
                      },
                      {
                        "type": "array",
                        "name": "race",
                        "sub": [
                          {
                            "type": "text",
                            "name": "$value"
                          }
                        ]
                      },
                      {
                        "type": "text",
                        "name": "shortId"
                      },
                      {
                        "type": "text",
                        "name": "suffix"
                      },
                      {
                        "type": "text",
                        "name": "transportStatus"
                      },
                      {
                        "type": "text",
                        "name": "user"
                      }
                    ]
                  },
                  {
                    "type": "array",
                    "name": "requests",
                    "sub": [
                      {
                        "type": "text",
                        "name": "approvalStatus"
                      },
                      {
                        "type": "object",
                        "name": "attributes",
                        "sub": [
                          {
                            "type": "text",
                            "name": "Colors (Color)"
                          },
                          {
                            "type": "text",
                            "name": "Shoe Size (Talla)"
                          }
                        ]
                      },
                      {
                        "type": "text",
                        "name": "attributesPretty"
                      },
                      {
                        "type": "text",
                        "name": "createdDatetime"
                      },
                      {
                        "type": "text",
                        "name": "id"
                      },
                      {
                        "type": "boolean",
                        "name": "isPurchased"
                      },
                      {
                        "type": "object",
                        "name": "item",
                        "sub": [
                          {
                            "type": "object",
                            "name": "category",
                            "sub": [
                              {
                                "type": "text",
                                "name": "createdDatetime"
                              },
                              {
                                "type": "text",
                                "name": "id"
                              },
                              {
                                "type": "text",
                                "name": "modifiedDatetime"
                              },
                              {
                                "type": "text",
                                "name": "name"
                              },
                              {
                                "type": "text",
                                "name": "shortId"
                              }
                            ]
                          },
                          {
                            "type": "text",
                            "name": "createdDatetime"
                          },
                          {
                            "type": "text",
                            "name": "description"
                          },
                          {
                            "type": "text",
                            "name": "icon"
                          },
                          {
                            "type": "text",
                            "name": "id"
                          },
                          {
                            "type": "number",
                            "name": "maximumPerWishlist"
                          },
                          {
                            "type": "text",
                            "name": "modifiedDatetime"
                          },
                          {
                            "type": "text",
                            "name": "name"
                          },
                          {
                            "type": "text",
                            "name": "shortId"
                          },
                          {
                            "type": "text",
                            "name": "status"
                          },
                          {
                            "type": "number",
                            "name": "valueInUsd"
                          }
                        ]
                      },
                      {
                        "type": "text",
                        "name": "modifiedDatetime"
                      },
                      {
                        "type": "text",
                        "name": "reviewNotes"
                      },
                      {
                        "type": "text",
                        "name": "shortId"
                      }
                    ]
                  },
                  {
                    "type": "text",
                    "name": "shortId"
                  },
                  {
                    "type": "array",
                    "name": "subWishlists"
                  },
                  {
                    "type": "text",
                    "name": "tagIdentifier"
                  },
                  {
                    "type": "number",
                    "name": "totalValueInUsd"
                  },
                  {
                    "type": "array",
                    "name": "wishlistQuestionResponses",
                    "sub": [
                      {
                        "type": "text",
                        "name": "type"
                      },
                      {
                        "type": "text",
                        "name": "label"
                      },
                      {
                        "type": "boolean",
                        "name": "required"
                      },
                      {
                        "type": "text",
                        "name": "response"
                      }
                    ]
                  },
                  {
                    "type": "text",
                    "name": "wishlistType"
                  }
                ]
              },
              {
                "type": "number",
                "name": "totalItems"
              }
            ]
          },
          {
            "type": "object",
            "name": "headers",
            "sub": [
              {
                "type": "text",
                "name": "apigw-requestid"
              },
              {
                "type": "text",
                "name": "content-length"
              },
              {
                "type": "text",
                "name": "content-type"
              },
              {
                "type": "text",
                "name": "date"
              }
            ]
          }
        ]
      },
      "output": true,
      "meta": [
        {
          "type": "object",
          "name": "data",
          "sub": [
            {
              "type": "text",
              "name": "message"
            },
            {
              "type": "array",
              "name": "data",
              "sub": [
                {
                  "type": "text",
                  "name": "bannerImage"
                },
                {
                  "type": "text",
                  "name": "circumstances"
                },
                {
                  "type": "text",
                  "name": "createdDatetime"
                },
                {
                  "type": "text",
                  "name": "donation"
                },
                {
                  "type": "text",
                  "name": "household"
                },
                {
                  "type": "number",
                  "name": "householdPosition"
                },
                {
                  "type": "number",
                  "name": "householdTotal"
                },
                {
                  "type": "text",
                  "name": "id"
                },
                {
                  "type": "text",
                  "name": "isPublic"
                },
                {
                  "type": "boolean",
                  "name": "isSponsored"
                },
                {
                  "type": "boolean",
                  "name": "isWishlistApproved"
                },
                {
                  "type": "text",
                  "name": "modifiedDatetime"
                },
                {
                  "type": "number",
                  "name": "numApprovedRequests"
                },
                {
                  "type": "number",
                  "name": "numPurchasedRequests"
                },
                {
                  "type": "number",
                  "name": "numTotalRequests"
                },
                {
                  "type": "object",
                  "name": "organization",
                  "sub": [
                    {
                      "type": "text",
                      "name": "bannerImageUrl"
                    },
                    {
                      "type": "text",
                      "name": "city"
                    },
                    {
                      "type": "text",
                      "name": "contactEmail"
                    },
                    {
                      "type": "text",
                      "name": "contactPhone"
                    },
                    {
                      "type": "text",
                      "name": "createdDatetime"
                    },
                    {
                      "type": "text",
                      "name": "description"
                    },
                    {
                      "type": "text",
                      "name": "domain"
                    },
                    {
                      "type": "text",
                      "name": "ein"
                    },
                    {
                      "type": "text",
                      "name": "email"
                    },
                    {
                      "type": "text",
                      "name": "facebook"
                    },
                    {
                      "type": "text",
                      "name": "href"
                    },
                    {
                      "type": "text",
                      "name": "id"
                    },
                    {
                      "type": "text",
                      "name": "instagram"
                    },
                    {
                      "type": "text",
                      "name": "latitude"
                    },
                    {
                      "type": "text",
                      "name": "linkedin"
                    },
                    {
                      "type": "text",
                      "name": "logoUrl"
                    },
                    {
                      "type": "text",
                      "name": "longitude"
                    },
                    {
                      "type": "text",
                      "name": "missionStatement"
                    },
                    {
                      "type": "text",
                      "name": "modifiedDatetime"
                    },
                    {
                      "type": "text",
                      "name": "name"
                    },
                    {
                      "type": "text",
                      "name": "organizationType"
                    },
                    {
                      "type": "text",
                      "name": "phone"
                    },
                    {
                      "type": "text",
                      "name": "postalCode"
                    },
                    {
                      "type": "text",
                      "name": "shortId"
                    },
                    {
                      "type": "text",
                      "name": "slug"
                    },
                    {
                      "type": "text",
                      "name": "state"
                    },
                    {
                      "type": "text",
                      "name": "streetAddress"
                    },
                    {
                      "type": "text",
                      "name": "streetAddress2"
                    },
                    {
                      "type": "object",
                      "name": "user",
                      "sub": [
                        {
                          "type": "text",
                          "name": "createdDatetime"
                        },
                        {
                          "type": "text",
                          "name": "email"
                        },
                        {
                          "type": "boolean",
                          "name": "emailSubscribed"
                        },
                        {
                          "type": "text",
                          "name": "id"
                        },
                        {
                          "type": "text",
                          "name": "modifiedDatetime"
                        },
                        {
                          "type": "text",
                          "name": "name"
                        },
                        {
                          "type": "text",
                          "name": "phone"
                        },
                        {
                          "type": "text",
                          "name": "referralSource"
                        },
                        {
                          "type": "boolean",
                          "name": "smsSubscribed"
                        },
                        {
                          "type": "text",
                          "name": "userId"
                        },
                        {
                          "type": "text",
                          "name": "userType"
                        },
                        {
                          "type": "text",
                          "name": "username"
                        }
                      ]
                    },
                    {
                      "type": "text",
                      "name": "websiteUrl"
                    }
                  ]
                },
                {
                  "type": "object",
                  "name": "parentWishlist",
                  "sub": [
                    {
                      "type": "text",
                      "name": "bannerImage"
                    },
                    {
                      "type": "text",
                      "name": "circumstances"
                    },
                    {
                      "type": "text",
                      "name": "createdDatetime"
                    },
                    {
                      "type": "text",
                      "name": "donation"
                    },
                    {
                      "type": "object",
                      "name": "household",
                      "sub": [
                        {
                          "type": "text",
                          "name": "city"
                        },
                        {
                          "type": "text",
                          "name": "createdDatetime"
                        },
                        {
                          "type": "text",
                          "name": "fullAddress"
                        },
                        {
                          "type": "array",
                          "name": "headsOfHousehold",
                          "sub": [
                            {
                              "type": "text",
                              "name": "age"
                            },
                            {
                              "type": "text",
                              "name": "createdDatetime"
                            },
                            {
                              "type": "text",
                              "name": "dateOfBirth"
                            },
                            {
                              "type": "text",
                              "name": "disabilityStatus"
                            },
                            {
                              "type": "text",
                              "name": "email"
                            },
                            {
                              "type": "text",
                              "name": "employmentStatus"
                            },
                            {
                              "type": "text",
                              "name": "ethnicity"
                            },
                            {
                              "type": "text",
                              "name": "firstName"
                            },
                            {
                              "type": "text",
                              "name": "fullName"
                            },
                            {
                              "type": "text",
                              "name": "gender"
                            },
                            {
                              "type": "text",
                              "name": "housingStatus"
                            },
                            {
                              "type": "text",
                              "name": "id"
                            },
                            {
                              "type": "text",
                              "name": "languagesSpoken"
                            },
                            {
                              "type": "text",
                              "name": "lastName"
                            },
                            {
                              "type": "text",
                              "name": "modifiedDatetime"
                            },
                            {
                              "type": "text",
                              "name": "personType"
                            },
                            {
                              "type": "text",
                              "name": "phone"
                            },
                            {
                              "type": "array",
                              "name": "race",
                              "sub": [
                                {
                                  "type": "text",
                                  "name": "$value"
                                }
                              ]
                            },
                            {
                              "type": "text",
                              "name": "shortId"
                            },
                            {
                              "type": "text",
                              "name": "suffix"
                            },
                            {
                              "type": "text",
                              "name": "transportStatus"
                            },
                            {
                              "type": "object",
                              "name": "user",
                              "sub": [
                                {
                                  "type": "text",
                                  "name": "createdDatetime"
                                },
                                {
                                  "type": "text",
                                  "name": "email"
                                },
                                {
                                  "type": "boolean",
                                  "name": "emailSubscribed"
                                },
                                {
                                  "type": "text",
                                  "name": "id"
                                },
                                {
                                  "type": "text",
                                  "name": "modifiedDatetime"
                                },
                                {
                                  "type": "text",
                                  "name": "name"
                                },
                                {
                                  "type": "text",
                                  "name": "phone"
                                },
                                {
                                  "type": "text",
                                  "name": "referralSource"
                                },
                                {
                                  "type": "boolean",
                                  "name": "smsSubscribed"
                                },
                                {
                                  "type": "text",
                                  "name": "userId"
                                },
                                {
                                  "type": "text",
                                  "name": "userType"
                                },
                                {
                                  "type": "text",
                                  "name": "username"
                                }
                              ]
                            },
                            {
                              "type": "text",
                              "name": "username"
                            }
                          ]
                        },
                        {
                          "type": "text",
                          "name": "householdIncome"
                        },
                        {
                          "type": "array",
                          "name": "householdMembers",
                          "sub": [
                            {
                              "type": "text",
                              "name": "age"
                            },
                            {
                              "type": "text",
                              "name": "createdDatetime"
                            },
                            {
                              "type": "text",
                              "name": "dateOfBirth"
                            },
                            {
                              "type": "text",
                              "name": "disabilityStatus"
                            },
                            {
                              "type": "text",
                              "name": "employmentStatus"
                            },
                            {
                              "type": "text",
                              "name": "ethnicity"
                            },
                            {
                              "type": "text",
                              "name": "firstName"
                            },
                            {
                              "type": "text",
                              "name": "fullName"
                            },
                            {
                              "type": "text",
                              "name": "gender"
                            },
                            {
                              "type": "text",
                              "name": "housingStatus"
                            },
                            {
                              "type": "text",
                              "name": "id"
                            },
                            {
                              "type": "text",
                              "name": "languagesSpoken"
                            },
                            {
                              "type": "text",
                              "name": "lastName"
                            },
                            {
                              "type": "text",
                              "name": "modifiedDatetime"
                            },
                            {
                              "type": "text",
                              "name": "personType"
                            },
                            {
                              "type": "array",
                              "name": "race",
                              "sub": [
                                {
                                  "type": "text",
                                  "name": "$value"
                                }
                              ]
                            },
                            {
                              "type": "text",
                              "name": "shortId"
                            },
                            {
                              "type": "text",
                              "name": "suffix"
                            },
                            {
                              "type": "text",
                              "name": "transportStatus"
                            },
                            {
                              "type": "text",
                              "name": "user"
                            }
                          ]
                        },
                        {
                          "type": "text",
                          "name": "id"
                        },
                        {
                          "type": "number",
                          "name": "latitude"
                        },
                        {
                          "type": "number",
                          "name": "longitude"
                        },
                        {
                          "type": "text",
                          "name": "modifiedDatetime"
                        },
                        {
                          "type": "text",
                          "name": "name"
                        },
                        {
                          "type": "text",
                          "name": "postalCode"
                        },
                        {
                          "type": "text",
                          "name": "shortId"
                        },
                        {
                          "type": "text",
                          "name": "state"
                        },
                        {
                          "type": "text",
                          "name": "streetAddress"
                        },
                        {
                          "type": "text",
                          "name": "streetAddress2"
                        }
                      ]
                    },
                    {
                      "type": "text",
                      "name": "householdPosition"
                    },
                    {
                      "type": "number",
                      "name": "householdTotal"
                    },
                    {
                      "type": "text",
                      "name": "id"
                    },
                    {
                      "type": "text",
                      "name": "isPublic"
                    },
                    {
                      "type": "boolean",
                      "name": "isSponsored"
                    },
                    {
                      "type": "boolean",
                      "name": "isWishlistApproved"
                    },
                    {
                      "type": "text",
                      "name": "modifiedDatetime"
                    },
                    {
                      "type": "number",
                      "name": "numApprovedRequests"
                    },
                    {
                      "type": "number",
                      "name": "numPurchasedRequests"
                    },
                    {
                      "type": "number",
                      "name": "numTotalRequests"
                    },
                    {
                      "type": "object",
                      "name": "organization",
                      "sub": [
                        {
                          "type": "text",
                          "name": "bannerImageUrl"
                        },
                        {
                          "type": "text",
                          "name": "city"
                        },
                        {
                          "type": "text",
                          "name": "contactEmail"
                        },
                        {
                          "type": "text",
                          "name": "contactPhone"
                        },
                        {
                          "type": "text",
                          "name": "createdDatetime"
                        },
                        {
                          "type": "text",
                          "name": "description"
                        },
                        {
                          "type": "text",
                          "name": "domain"
                        },
                        {
                          "type": "text",
                          "name": "ein"
                        },
                        {
                          "type": "text",
                          "name": "email"
                        },
                        {
                          "type": "text",
                          "name": "facebook"
                        },
                        {
                          "type": "text",
                          "name": "href"
                        },
                        {
                          "type": "text",
                          "name": "id"
                        },
                        {
                          "type": "text",
                          "name": "instagram"
                        },
                        {
                          "type": "text",
                          "name": "latitude"
                        },
                        {
                          "type": "text",
                          "name": "linkedin"
                        },
                        {
                          "type": "text",
                          "name": "logoUrl"
                        },
                        {
                          "type": "text",
                          "name": "longitude"
                        },
                        {
                          "type": "text",
                          "name": "missionStatement"
                        },
                        {
                          "type": "text",
                          "name": "modifiedDatetime"
                        },
                        {
                          "type": "text",
                          "name": "name"
                        },
                        {
                          "type": "text",
                          "name": "organizationType"
                        },
                        {
                          "type": "text",
                          "name": "phone"
                        },
                        {
                          "type": "text",
                          "name": "postalCode"
                        },
                        {
                          "type": "text",
                          "name": "shortId"
                        },
                        {
                          "type": "text",
                          "name": "slug"
                        },
                        {
                          "type": "text",
                          "name": "state"
                        },
                        {
                          "type": "text",
                          "name": "streetAddress"
                        },
                        {
                          "type": "text",
                          "name": "streetAddress2"
                        },
                        {
                          "type": "object",
                          "name": "user",
                          "sub": [
                            {
                              "type": "text",
                              "name": "createdDatetime"
                            },
                            {
                              "type": "text",
                              "name": "email"
                            },
                            {
                              "type": "boolean",
                              "name": "emailSubscribed"
                            },
                            {
                              "type": "text",
                              "name": "id"
                            },
                            {
                              "type": "text",
                              "name": "modifiedDatetime"
                            },
                            {
                              "type": "text",
                              "name": "name"
                            },
                            {
                              "type": "text",
                              "name": "phone"
                            },
                            {
                              "type": "text",
                              "name": "referralSource"
                            },
                            {
                              "type": "boolean",
                              "name": "smsSubscribed"
                            },
                            {
                              "type": "text",
                              "name": "userId"
                            },
                            {
                              "type": "text",
                              "name": "userType"
                            },
                            {
                              "type": "text",
                              "name": "username"
                            }
                          ]
                        },
                        {
                          "type": "text",
                          "name": "websiteUrl"
                        }
                      ]
                    },
                    {
                      "type": "text",
                      "name": "parentWishlist"
                    },
                    {
                      "type": "text",
                      "name": "pickupTimeslot"
                    },
                    {
                      "type": "object",
                      "name": "program",
                      "sub": [
                        {
                          "type": "boolean",
                          "name": "allowInKindDonations"
                        },
                        {
                          "type": "boolean",
                          "name": "allowMonetaryDonations"
                        },
                        {
                          "type": "text",
                          "name": "applicationReasonText"
                        },
                        {
                          "type": "text",
                          "name": "id"
                        },
                        {
                          "type": "text",
                          "name": "maximumDateOfBirth"
                        },
                        {
                          "type": "number",
                          "name": "maximumWishlistLength"
                        },
                        {
                          "type": "text",
                          "name": "minimumDateOfBirth"
                        },
                        {
                          "type": "number",
                          "name": "minimumWishlistLength"
                        },
                        {
                          "type": "text",
                          "name": "name"
                        },
                        {
                          "type": "object",
                          "name": "owner",
                          "sub": [
                            {
                              "type": "text",
                              "name": "domain"
                            },
                            {
                              "type": "text",
                              "name": "id"
                            },
                            {
                              "type": "text",
                              "name": "name"
                            },
                            {
                              "type": "text",
                              "name": "slug"
                            }
                          ]
                        },
                        {
                          "type": "text",
                          "name": "slug"
                        },
                        {
                          "type": "text",
                          "name": "sponsorshipType"
                        },
                        {
                          "type": "array",
                          "name": "wishlistQuestions",
                          "sub": [
                            {
                              "type": "text",
                              "name": "type"
                            },
                            {
                              "type": "text",
                              "name": "label"
                            },
                            {
                              "type": "boolean",
                              "name": "required"
                            }
                          ]
                        }
                      ]
                    },
                    {
                      "type": "text",
                      "name": "recipient"
                    },
                    {
                      "type": "array",
                      "name": "requests"
                    },
                    {
                      "type": "text",
                      "name": "shortId"
                    },
                    {
                      "type": "text",
                      "name": "tagIdentifier"
                    },
                    {
                      "type": "number",
                      "name": "totalValueInUsd"
                    },
                    {
                      "type": "text",
                      "name": "wishlistQuestionResponses"
                    },
                    {
                      "type": "text",
                      "name": "wishlistType"
                    }
                  ]
                },
                {
                  "type": "text",
                  "name": "pickupTimeslot"
                },
                {
                  "type": "object",
                  "name": "program",
                  "sub": [
                    {
                      "type": "boolean",
                      "name": "allowInKindDonations"
                    },
                    {
                      "type": "boolean",
                      "name": "allowMonetaryDonations"
                    },
                    {
                      "type": "text",
                      "name": "applicationReasonText"
                    },
                    {
                      "type": "text",
                      "name": "id"
                    },
                    {
                      "type": "text",
                      "name": "maximumDateOfBirth"
                    },
                    {
                      "type": "number",
                      "name": "maximumWishlistLength"
                    },
                    {
                      "type": "text",
                      "name": "minimumDateOfBirth"
                    },
                    {
                      "type": "number",
                      "name": "minimumWishlistLength"
                    },
                    {
                      "type": "text",
                      "name": "name"
                    },
                    {
                      "type": "object",
                      "name": "owner",
                      "sub": [
                        {
                          "type": "text",
                          "name": "domain"
                        },
                        {
                          "type": "text",
                          "name": "id"
                        },
                        {
                          "type": "text",
                          "name": "name"
                        },
                        {
                          "type": "text",
                          "name": "slug"
                        }
                      ]
                    },
                    {
                      "type": "text",
                      "name": "slug"
                    },
                    {
                      "type": "text",
                      "name": "sponsorshipType"
                    },
                    {
                      "type": "array",
                      "name": "wishlistQuestions",
                      "sub": [
                        {
                          "type": "text",
                          "name": "type"
                        },
                        {
                          "type": "text",
                          "name": "label"
                        },
                        {
                          "type": "boolean",
                          "name": "required"
                        }
                      ]
                    }
                  ]
                },
                {
                  "type": "object",
                  "name": "recipient",
                  "sub": [
                    {
                      "type": "text",
                      "name": "age"
                    },
                    {
                      "type": "text",
                      "name": "createdDatetime"
                    },
                    {
                      "type": "text",
                      "name": "dateOfBirth"
                    },
                    {
                      "type": "text",
                      "name": "disabilityStatus"
                    },
                    {
                      "type": "text",
                      "name": "employmentStatus"
                    },
                    {
                      "type": "text",
                      "name": "ethnicity"
                    },
                    {
                      "type": "text",
                      "name": "firstName"
                    },
                    {
                      "type": "text",
                      "name": "fullName"
                    },
                    {
                      "type": "text",
                      "name": "gender"
                    },
                    {
                      "type": "object",
                      "name": "household",
                      "sub": [
                        {
                          "type": "text",
                          "name": "city"
                        },
                        {
                          "type": "text",
                          "name": "createdDatetime"
                        },
                        {
                          "type": "text",
                          "name": "fullAddress"
                        },
                        {
                          "type": "text",
                          "name": "householdIncome"
                        },
                        {
                          "type": "text",
                          "name": "id"
                        },
                        {
                          "type": "number",
                          "name": "latitude"
                        },
                        {
                          "type": "number",
                          "name": "longitude"
                        },
                        {
                          "type": "text",
                          "name": "modifiedDatetime"
                        },
                        {
                          "type": "text",
                          "name": "name"
                        },
                        {
                          "type": "text",
                          "name": "postalCode"
                        },
                        {
                          "type": "text",
                          "name": "shortId"
                        },
                        {
                          "type": "text",
                          "name": "state"
                        },
                        {
                          "type": "text",
                          "name": "streetAddress"
                        },
                        {
                          "type": "text",
                          "name": "streetAddress2"
                        }
                      ]
                    },
                    {
                      "type": "text",
                      "name": "housingStatus"
                    },
                    {
                      "type": "text",
                      "name": "id"
                    },
                    {
                      "type": "text",
                      "name": "languagesSpoken"
                    },
                    {
                      "type": "text",
                      "name": "lastName"
                    },
                    {
                      "type": "text",
                      "name": "modifiedDatetime"
                    },
                    {
                      "type": "text",
                      "name": "personType"
                    },
                    {
                      "type": "array",
                      "name": "race",
                      "sub": [
                        {
                          "type": "text",
                          "name": "$value"
                        }
                      ]
                    },
                    {
                      "type": "text",
                      "name": "shortId"
                    },
                    {
                      "type": "text",
                      "name": "suffix"
                    },
                    {
                      "type": "text",
                      "name": "transportStatus"
                    },
                    {
                      "type": "text",
                      "name": "user"
                    }
                  ]
                },
                {
                  "type": "array",
                  "name": "requests",
                  "sub": [
                    {
                      "type": "text",
                      "name": "approvalStatus"
                    },
                    {
                      "type": "object",
                      "name": "attributes",
                      "sub": [
                        {
                          "type": "text",
                          "name": "Colors (Color)"
                        },
                        {
                          "type": "text",
                          "name": "Shoe Size (Talla)"
                        }
                      ]
                    },
                    {
                      "type": "text",
                      "name": "attributesPretty"
                    },
                    {
                      "type": "text",
                      "name": "createdDatetime"
                    },
                    {
                      "type": "text",
                      "name": "id"
                    },
                    {
                      "type": "boolean",
                      "name": "isPurchased"
                    },
                    {
                      "type": "object",
                      "name": "item",
                      "sub": [
                        {
                          "type": "object",
                          "name": "category",
                          "sub": [
                            {
                              "type": "text",
                              "name": "createdDatetime"
                            },
                            {
                              "type": "text",
                              "name": "id"
                            },
                            {
                              "type": "text",
                              "name": "modifiedDatetime"
                            },
                            {
                              "type": "text",
                              "name": "name"
                            },
                            {
                              "type": "text",
                              "name": "shortId"
                            }
                          ]
                        },
                        {
                          "type": "text",
                          "name": "createdDatetime"
                        },
                        {
                          "type": "text",
                          "name": "description"
                        },
                        {
                          "type": "text",
                          "name": "icon"
                        },
                        {
                          "type": "text",
                          "name": "id"
                        },
                        {
                          "type": "number",
                          "name": "maximumPerWishlist"
                        },
                        {
                          "type": "text",
                          "name": "modifiedDatetime"
                        },
                        {
                          "type": "text",
                          "name": "name"
                        },
                        {
                          "type": "text",
                          "name": "shortId"
                        },
                        {
                          "type": "text",
                          "name": "status"
                        },
                        {
                          "type": "number",
                          "name": "valueInUsd"
                        }
                      ]
                    },
                    {
                      "type": "text",
                      "name": "modifiedDatetime"
                    },
                    {
                      "type": "text",
                      "name": "reviewNotes"
                    },
                    {
                      "type": "text",
                      "name": "shortId"
                    }
                  ]
                },
                {
                  "type": "text",
                  "name": "shortId"
                },
                {
                  "type": "array",
                  "name": "subWishlists"
                },
                {
                  "type": "text",
                  "name": "tagIdentifier"
                },
                {
                  "type": "number",
                  "name": "totalValueInUsd"
                },
                {
                  "type": "array",
                  "name": "wishlistQuestionResponses",
                  "sub": [
                    {
                      "type": "text",
                      "name": "type"
                    },
                    {
                      "type": "text",
                      "name": "label"
                    },
                    {
                      "type": "boolean",
                      "name": "required"
                    },
                    {
                      "type": "text",
                      "name": "response"
                    }
                  ]
                },
                {
                  "type": "text",
                  "name": "wishlistType"
                }
              ]
            },
            {
              "type": "number",
              "name": "totalItems"
            }
          ]
        },
        {
          "type": "object",
          "name": "headers",
          "sub": [
            {
              "type": "text",
              "name": "apigw-requestid"
            },
            {
              "type": "text",
              "name": "content-length"
            },
            {
              "type": "text",
              "name": "content-type"
            },
            {
              "type": "text",
              "name": "date"
            }
          ]
        }
      ],
      "outputType": "object"
    }
  }
}